thonnycontrib/__init__.py
thonnycontrib/quecpython/__init__.py
thonnycontrib/quecpython/api.py
thonnycontrib/quecpython/view.py
thonnycontrib/quecpython/backend/__init__.py
thonnycontrib/quecpython/backend/bare_metal_backend.py
thonnycontrib/quecpython/backend/base_flashing_dialog.py
thonnycontrib/quecpython/backend/connection.py
thonnycontrib/quecpython/backend/esptool_dialog.py
thonnycontrib/quecpython/backend/miniterm_wrapper.py
thonnycontrib/quecpython/backend/mp_back.py
thonnycontrib/quecpython/backend/mp_common.py
thonnycontrib/quecpython/backend/mp_front.py
thonnycontrib/quecpython/backend/os_mp_backend.py
thonnycontrib/quecpython/backend/pip_gui.py
thonnycontrib/quecpython/backend/serial_connection.py
thonnycontrib/quecpython/backend/ssh_connection.py
thonnycontrib/quecpython/backend/subprocess_connection.py
thonnycontrib/quecpython/backend/uf2dialog.py
thonnycontrib/quecpython/backend/webrepl_connection.py
thonnycontrib/quecpython/backend/base_api_stubs/LICENSE
thonnycontrib/quecpython/backend/base_api_stubs/__init__.pyi
thonnycontrib/quecpython/backend/base_api_stubs/__main__.py
thonnycontrib/quecpython/backend/base_api_stubs/_thread.pyi
thonnycontrib/quecpython/backend/base_api_stubs/app_fota.pyi
thonnycontrib/quecpython/backend/base_api_stubs/array.pyi
thonnycontrib/quecpython/backend/base_api_stubs/atcmd.pyi
thonnycontrib/quecpython/backend/base_api_stubs/audio.pyi
thonnycontrib/quecpython/backend/base_api_stubs/binascii.pyi
thonnycontrib/quecpython/backend/base_api_stubs/ble.pyi
thonnycontrib/quecpython/backend/base_api_stubs/bluetooth.pyi
thonnycontrib/quecpython/backend/base_api_stubs/bt.pyi
thonnycontrib/quecpython/backend/base_api_stubs/btree.pyi
thonnycontrib/quecpython/backend/base_api_stubs/camera.pyi
thonnycontrib/quecpython/backend/base_api_stubs/cellLocator.pyi
thonnycontrib/quecpython/backend/base_api_stubs/checkNet.pyi
thonnycontrib/quecpython/backend/base_api_stubs/cmath.pyi
thonnycontrib/quecpython/backend/base_api_stubs/collections.pyi
thonny_quecpython-0.2.4.dist-info/LICENSE
thonny_quecpython-0.2.4.dist-info/METADATA
thonny_quecpython-0.2.4.dist-info/WHEEL
thonny_quecpython-0.2.4.dist-info/top_level.txt
thonny_quecpython-0.2.4.dist-info/RECORD
