Metadata-Version: 2.1
Name: thonny-quecpython
Version: 0.2.4
Summary: quecpython programing kits for thonny
Home-page: https://github.com/QuecPython/thonny-quecpython
Author: dustin.wei
Author-email: dustin.wei@quectel.com
License: MIT License
Keywords: QuecPython,quecpython,QuecPython Kits,quecpython kits
Platform: windows
Classifier: Programming Language :: Python :: 3
Classifier: License :: OSI Approved :: MIT License
Classifier: Operating System :: OS Independent
Requires-Python: >=3.7
License-File: LICENSE
Requires-Dist: thonny (>=4.1.1)
Requires-Dist: Pypubsub (>=4.0.3)
